lrbd.py
lrbd/__init__.py
lrbd/bd.py
lrbd/lrbd.py
lrbd/utils.py
lrbd-0.4.dist-info/LICENSE
lrbd-0.4.dist-info/METADATA
lrbd-0.4.dist-info/WHEEL
lrbd-0.4.dist-info/top_level.txt
lrbd-0.4.dist-info/RECORD
